carrottransform/__init__.py
carrottransform/_version.py
carrottransform/cli/__init__.py
carrottransform/cli/command.py
carrottransform/cli/subcommands/__init__.py
carrottransform/cli/subcommands/run.py
carrottransform/config/OMOPCDM_postgresql_5.3_ddl.sql
carrottransform/config/omop.json
carrottransform/tools/__init__.py
carrottransform/tools/file_helpers.py
carrottransform/tools/mappingrules.py
carrottransform/tools/metrics.py
carrottransform/tools/omopcdm.py
carrottransform-0.3.dist-info/LICENSE
carrottransform-0.3.dist-info/METADATA
carrottransform-0.3.dist-info/WHEEL
carrottransform-0.3.dist-info/entry_points.txt
carrottransform-0.3.dist-info/top_level.txt
carrottransform-0.3.dist-info/RECORD
