Metadata-Version: 2.1
Name: carrottransform
Version: 0.3
Summary: Carrot somple transformer, input rules and data csvs, output OMOP
Author-email: PD Appleby <pdappleby@gmail.com>
Classifier: Programming Language :: Python :: 3
Classifier: License :: OSI Approved :: MIT License
Classifier: Operating System :: OS Independent
Requires-Python: >=3.9
License-File: LICENSE
